aimrocks/lib_rocksdb.cpython-36m-aarch64-linux-gnu.so
aimrocks/filter_policy.pxd
aimrocks/logger.pxd
aimrocks/status.pxd
aimrocks/lib_utils.py
aimrocks/iterator.pxd
aimrocks/db.pxd
aimrocks/interfaces.py
aimrocks/cache.pxd
aimrocks/options.pxd
aimrocks/lib_rocksdb.pyi
aimrocks/table_factory.pxd
aimrocks/lib_rocksdb.pxd
aimrocks/__init__.py
aimrocks/lib_rocksdb.cpp
aimrocks/lib_rocksdb.pyx
aimrocks/env.pxd
aimrocks/merge_operator.pxd
aimrocks/std_memory.pxd
aimrocks/comparator.pxd
aimrocks/errors.py
aimrocks/memtablerep.pxd
aimrocks/backup.pxd
aimrocks/universal_compaction.pxd
aimrocks/librocksdb.so
aimrocks/slice_transform.pxd
aimrocks/merge_operators.py
aimrocks/slice_.pxd
aimrocks/snapshot.pxd
aimrocks/include/rocksdb/memtablerep.h
aimrocks/include/rocksdb/file_checksum.h
aimrocks/include/rocksdb/wal_filter.h
aimrocks/include/rocksdb/listener.h
aimrocks/include/rocksdb/system_clock.h
aimrocks/include/rocksdb/advanced_options.h
aimrocks/include/rocksdb/c.h
aimrocks/include/rocksdb/configurable.h
aimrocks/include/rocksdb/perf_level.h
aimrocks/include/rocksdb/write_batch_base.h
aimrocks/include/rocksdb/transaction_log.h
aimrocks/include/rocksdb/comparator.h
aimrocks/include/rocksdb/cache_bench_tool.h
aimrocks/include/rocksdb/thread_status.h
aimrocks/include/rocksdb/rocksdb_namespace.h
aimrocks/include/rocksdb/filter_policy.h
aimrocks/include/rocksdb/data_structure.h
aimrocks/include/rocksdb/sst_file_manager.h
aimrocks/include/rocksdb/threadpool.h
aimrocks/include/rocksdb/iostats_context.h
aimrocks/include/rocksdb/unique_id.h
aimrocks/include/rocksdb/statistics.h
aimrocks/include/rocksdb/file_system.h
aimrocks/include/rocksdb/functor_wrapper.h
aimrocks/include/rocksdb/stats_history.h
aimrocks/include/rocksdb/customizable.h
aimrocks/include/rocksdb/write_batch.h
aimrocks/include/rocksdb/trace_record.h
aimrocks/include/rocksdb/trace_record_result.h
aimrocks/include/rocksdb/table.h
aimrocks-0.5.2.dist-info/top_level.txt
aimrocks-0.5.2.dist-info/METADATA
aimrocks-0.5.2.dist-info/LICENSE
aimrocks-0.5.2.dist-info/WHEEL
aimrocks-0.5.2.dist-info/RECORD
